baiduSpiderCreatedByHanXu/__init__.py
baiduSpiderCreatedByHanXu/spider.py
baiduSpiderCreatedByHanXu-0.0.3.dist-info/LICENSE
baiduSpiderCreatedByHanXu-0.0.3.dist-info/METADATA
baiduSpiderCreatedByHanXu-0.0.3.dist-info/WHEEL
baiduSpiderCreatedByHanXu-0.0.3.dist-info/top_level.txt
baiduSpiderCreatedByHanXu-0.0.3.dist-info/RECORD
